azure/mgmt/compute/__init__.py
azure/mgmt/compute/_compute_management_client.py
azure/mgmt/compute/_configuration.py
azure/mgmt/compute/_serialization.py
azure/mgmt/compute/_version.py
azure/mgmt/compute/models.py
azure/mgmt/compute/py.typed
azure/mgmt/compute/aio/__init__.py
azure/mgmt/compute/aio/_compute_management_client.py
azure/mgmt/compute/aio/_configuration.py
azure/mgmt/compute/v2016_03_30/__init__.py
azure/mgmt/compute/v2016_03_30/_compute_management_client.py
azure/mgmt/compute/v2016_03_30/_configuration.py
azure/mgmt/compute/v2016_03_30/_patch.py
azure/mgmt/compute/v2016_03_30/_version.py
azure/mgmt/compute/v2016_03_30/py.typed
azure/mgmt/compute/v2016_03_30/aio/__init__.py
azure/mgmt/compute/v2016_03_30/aio/_compute_management_client.py
azure/mgmt/compute/v2016_03_30/aio/_configuration.py
azure/mgmt/compute/v2016_03_30/aio/_patch.py
azure/mgmt/compute/v2016_03_30/aio/operations/__init__.py
azure/mgmt/compute/v2016_03_30/aio/operations/_operations.py
azure/mgmt/compute/v2016_03_30/aio/operations/_patch.py
azure/mgmt/compute/v2016_03_30/models/__init__.py
azure/mgmt/compute/v2016_03_30/models/_compute_management_client_enums.py
azure/mgmt/compute/v2016_03_30/models/_models_py3.py
azure/mgmt/compute/v2016_03_30/models/_patch.py
azure/mgmt/compute/v2016_03_30/operations/__init__.py
azure/mgmt/compute/v2016_03_30/operations/_operations.py
azure/mgmt/compute/v2016_03_30/operations/_patch.py
azure/mgmt/compute/v2017_03_30/__init__.py
azure/mgmt/compute/v2017_03_30/_compute_management_client.py
azure/mgmt/compute/v2017_03_30/_configuration.py
azure/mgmt/compute/v2017_03_30/_patch.py
azure/mgmt/compute/v2017_03_30/_version.py
azure/mgmt/compute/v2017_03_30/py.typed
azure/mgmt/compute/v2017_03_30/aio/__init__.py
azure/mgmt/compute/v2017_03_30/aio/_compute_management_client.py
azure/mgmt/compute/v2017_03_30/aio/_configuration.py
azure/mgmt/compute/v2017_03_30/aio/_patch.py
azure/mgmt/compute/v2017_03_30/aio/operations/__init__.py
azure_mgmt_compute-34.0.0.dist-info/LICENSE
azure_mgmt_compute-34.0.0.dist-info/METADATA
azure_mgmt_compute-34.0.0.dist-info/WHEEL
azure_mgmt_compute-34.0.0.dist-info/top_level.txt
azure_mgmt_compute-34.0.0.dist-info/RECORD
